sortbyname/__init__.py
sortbyname/sortbyname.py
sortbyname-0.0.1.dist-info/LICENSE
sortbyname-0.0.1.dist-info/METADATA
sortbyname-0.0.1.dist-info/WHEEL
sortbyname-0.0.1.dist-info/top_level.txt
sortbyname-0.0.1.dist-info/RECORD
