Metadata-Version: 2.1
Name: sortbyname
Version: 0.0.1
Summary: .
Home-page: https://github.com/seoul2k/sortbyname
Author: xiongtianshuo
Author-email: Mr_Xiongts@163.com
License: UNKNOWN
Project-URL: Bug Tracker, https://github.com/seoul2k/sortbyname/issues
Platform: UNKNOWN
Classifier: Development Status :: 4 - Beta
Classifier: Operating System :: OS Independent
Classifier: Intended Audience :: Developers
Classifier: License :: OSI Approved :: BSD License
Classifier: Programming Language :: Python :: 2.7
Classifier: Programming Language :: Python :: Implementation
Classifier: Programming Language :: Python :: 3
Classifier: Programming Language :: Python :: 3.4
Classifier: Programming Language :: Python :: 3.5
Classifier: Programming Language :: Python :: 3.6
Classifier: Programming Language :: Python :: 3.8
Classifier: Topic :: Software Development :: Libraries
Requires-Python: >=3
License-File: LICENSE
Requires-Dist: pinyin
